graft_cli/__init__.py
graft_cli/compile_elm.py
graft_cli/main.py
graft_cli/p_assert.py
graft_cli/rust_json.py
graft_cli-0.0.1.dist-info/LICENSE
graft_cli-0.0.1.dist-info/METADATA
graft_cli-0.0.1.dist-info/WHEEL
graft_cli-0.0.1.dist-info/entry_points.txt
graft_cli-0.0.1.dist-info/top_level.txt
graft_cli-0.0.1.dist-info/RECORD
