Metadata-Version: 2.1
Name: graft-cli
Version: 0.0.1
Summary: A command line utitily to provide services offered by graftpress( a graft-elm web framework).
Home-page: https://github.com/amitu/graftpress/
Author: nilinswap
Author-email: nilinswap@gmail.com
License: UNKNOWN
Platform: UNKNOWN
Requires-Dist: cookiecutter (>=1.6.0)
